{
    "name": "Doposażenie zabytkowego parku w infrastrukturę techniczną, w postaci budowy toalety publicznej celem podniesienie jakości i funkcjonalności przestrzeni publicznej",
    "description": "Nr referencyjny umowy: ZT25-00597<br>Data zawarcia umowy pożyczki: 2/10/2025<br>Kwota pożyczki:   450,000.0 <br>Nazwa pożyczkobiorcy: GMINA ŚWIDNICA<br>Lokalizacja: 51.94306402069312, 15.51784250897405<br>1 Lokalizacja/Miasto Inwestycji: Zielona Góra<br>Opis projektu: Przedmiotem projektu jest budowa wolnostojącego budynku toalety w historycznym parku w Letnicy znajdującym się między budynkiem Zboru poewangelickiego, a Dworem pałacowym. Inwestycja polega na doposażeniu terenów zieleni w infrastrukturę sanitarną zachęcającą do korzystania z publicznych terenów zieleni – (przed realizacją projektu w parku w sezonie wiosenno-letnim dostępna była tylko tymczasowa toaleta typu toi-toi). <br>Budynek toalety stanowić będzie również  funkcję uzupełniającą dla istniejącego domu kultury (Zboru) z przeznaczeniem  dla użytkowników budynku kulturalnego. Budynek toalety składać się będzie z toalety męskiej, damskiej oraz dla osób niepełnosprawnych, a także pomieszczenia gospodarczego. Aby zapewnić swobodny dostęp do budynku toalet osobom niepełnosprawnym zaprojektowano niwelację terenu i dojścia do budynku, a także brak występowania progów o wysokości większej niż 2 cm. Toalety mają być wyposażone w automatyczny system spłukiwania, które minimalizują zużycie wody (umywalki, miski ustępowe, pisuary), a także energooszczędne oświetlenie LED. Zbór w Letnicy jest miejscem o ugruntowanej renomie na mapie kulturalnej województwa lubuskiego, przyciąga artystów i miłośników sztuki z całej Polski, a także z zagranicy. Wydarzenia takie jak Festiwal Muzyka w Raju czy koncerty Lubuszanie in Memoriam gromadzą liczne grono uczestników nie tylko z Letnicy, ale także z terenów wiejskich MOF/ZNOF jak i z miast wchodzących w jego skład, w tym z Zielonej Góry. Zapewnienie odpowiedniej infrastruktury sanitarno-technicznej, jaką są nowoczesne toalety, jest kluczowe dla utrzymania atrakcyjności zboru jako miejsca organizacji wydarzeń na skalę regionalną i międzynarodową.<br>Rezultatem zadania będzie poprawa warunków higieniczno-sanitarnych w parku przy obiekcie kulturowym dzięki doposażeniu go w budynek toalet. Budowa toalety publicznej (ogólnodostępnej i nieodpłatnej) pozwoli na zmniejszenie zanieczyszczeń w parku – przyczyni się do ograniczenia przypadków zaśmiecania oraz nieodpowiedniego korzystania z przestrzeni zielonych. Ponadto  wpłynie na poprawę jakości życia mieszkańców MOF/ZNOF, a także artystów i turystów odwiedzających to miejsce. Budowa toalety pozytywie wpłynie na wizerunek parku oraz zwiększy komfort i zadowolenie z jego korzystania, podniesie standard estetyczny i funkcjonalny zielonej przestrzeni publicznej.",
    "styleUrl": "#icon-1886-7CB342",
    "Nr referencyjny umowy": "ZT25-00597",
    "Data zawarcia umowy pożyczki": "2/10/2025",
    "Kwota pożyczki": "  450,000.0 ",
    "Nazwa pożyczkobiorcy": "GMINA ŚWIDNICA",
    "Lokalizacja": "51.94306402069312, 15.51784250897405",
    "1 Lokalizacja/Miasto Inwestycji": "Zielona Góra",
    "Opis projektu": "Przedmiotem projektu jest budowa wolnostojącego budynku toalety w historycznym parku w Letnicy znajdującym się między budynkiem Zboru poewangelickiego, a Dworem pałacowym. Inwestycja polega na doposażeniu terenów zieleni w infrastrukturę sanitarną zachęcającą do korzystania z publicznych terenów zieleni – (przed realizacją projektu w parku w sezonie wiosenno-letnim dostępna była tylko tymczasowa toaleta typu toi-toi). \nBudynek toalety stanowić będzie również  funkcję uzupełniającą dla istniejącego domu kultury (Zboru) z przeznaczeniem  dla użytkowników budynku kulturalnego. Budynek toalety składać się będzie z toalety męskiej, damskiej oraz dla osób niepełnosprawnych, a także pomieszczenia gospodarczego. Aby zapewnić swobodny dostęp do budynku toalet osobom niepełnosprawnym zaprojektowano niwelację terenu i dojścia do budynku, a także brak występowania progów o wysokości większej niż 2 cm. Toalety mają być wyposażone w automatyczny system spłukiwania, które minimalizują zużycie wody (umywalki, miski ustępowe, pisuary), a także energooszczędne oświetlenie LED. Zbór w Letnicy jest miejscem o ugruntowanej renomie na mapie kulturalnej województwa lubuskiego, przyciąga artystów i miłośników sztuki z całej Polski, a także z zagranicy. Wydarzenia takie jak Festiwal Muzyka w Raju czy koncerty Lubuszanie in Memoriam gromadzą liczne grono uczestników nie tylko z Letnicy, ale także z terenów wiejskich MOF/ZNOF jak i z miast wchodzących w jego skład, w tym z Zielonej Góry. Zapewnienie odpowiedniej infrastruktury sanitarno-technicznej, jaką są nowoczesne toalety, jest kluczowe dla utrzymania atrakcyjności zboru jako miejsca organizacji wydarzeń na skalę regionalną i międzynarodową.\nRezultatem zadania będzie poprawa warunków higieniczno-sanitarnych w parku przy obiekcie kulturowym dzięki doposażeniu go w budynek toalet. Budowa toalety publicznej (ogólnodostępnej i nieodpłatnej) pozwoli na zmniejszenie zanieczyszczeń w parku – przyczyni się do ograniczenia przypadków zaśmiecania oraz nieodpowiedniego korzystania z przestrzeni zielonych. Ponadto  wpłynie na poprawę jakości życia mieszkańców MOF/ZNOF, a także artystów i turystów odwiedzających to miejsce. Budowa toalety pozytywie wpłynie na wizerunek parku oraz zwiększy komfort i zadowolenie z jego korzystania, podniesie standard estetyczny i funkcjonalny zielonej przestrzeni publicznej."
}