{
    "name": "Budowa ścieżki rowerowej przez teren gminy Świdnica do Nowogrodu Bobrzańskiego; będącej odcinkiem transgranicznej ścieżki rowerowej od zachodnich okolic miejscowości Lubsko do granicy miasta Zielona Góra przez gminy ZNOF Świdnica-Nowogród Bobrzański – etap II",
    "description": "Nr referencyjny umowy: ZT25-00596<br>Data zawarcia umowy pożyczki: 2/10/2025<br>Kwota pożyczki:   1,650,000.0 <br>Nazwa pożyczkobiorcy: GMINA ŚWIDNICA<br>Lokalizacja: 51.886571541478475, 15.382544818873686<br>1 Lokalizacja/Miasto Inwestycji: Zielona Góra<br>Opis projektu: Przedmiotem projektu jest budowa ścieżki rowerowej o łącznej długości ok. 2,5 km relacji Zielona Góra-Wilkanowo – etap II. Projekt realizowany będzie w województwie lubuskim, w gminie wiejskiej Świdnica na terenie MOF/ZNOF.  Wyznaczona trasa przebiegu ścieżki rowerowej na terenie gminy Świdnica przebiega wzdłuż pasa drogi wojewódzkiej nr 282, głównie na terenach leśnych i wzdłuż działek drogowych do ronda południowej obwodnicy miasta Zielona Góra. Jest to kontynuacja budowy ścieżki rowerowej wytyczonej w ramach projektu ODRA-VELO, która  połączy miejscowość Wilkanowo ze ścieżką na terenie miasta Zielona Góra, a docelowo połączy gminy ZNOF od granicy miasta Zielona Góra przez Gminy ZNOF Świdnica - Nowogród Bobrzański. Realizacja projektu przyczyni się do rozwiązania problemów zdiagnozowanych w obszarze transportu  i komunikacji indywidualnej na terenie obszaru ZNOF oraz województwa lubuskiego, czyli zwiększy spójność ścieżek rowerowych, umożliwi dostęp do komunikacji zeroemisyjnej jaką jest transport rowerowy, co będzie miało przełożenie na zmniejszenie zanieczyszczenia powietrza (minimalizacja CO2 do powietrza dzięki zmniejszeniu ruchu tradycyjnego spalinowego na rzecz transportu rowerowego). Zmniejszy zagrożenie wypadkiem z powodu niewystarczającego poziomu infrastruktury dedykowanej rowerzystom, a także wpłynie na poprawę jakości życia i zdrowia mieszkańców. <br>Z rezultatów projektu tj. wybudowanego odcinka ścieżki rowerowej będą korzystać osoby bezpośrednio związane z tym terenem tj. mieszkańcy Wilkanowa, Zielonej Góry, Świdnicy jak i Nowogrodu Bobrzańskiego, niemniej jednak cała społeczność regionu odniesie pozytywną korzyść z powstałej infrastruktury poprzez możliwość przebywania w czystszym środowisku, uprawiania turystyki aktywnej oraz zdobycie szerokiej wiedzy na temat otaczającego środowiska naturalnego.<br>Ścieżka, łącząc różne obszary w ramach MOF/ZNOF, przyczynia się do poprawy dostępności komunikacyjnej i integracji przestrzennej. Dla obszarów wiejskich oznacza to lepsze możliwości rozwoju turystyki, aktywizacji gospodarczej i poprawę jakości życia. Z kolei dla miasta, takiego jak Zielona Góra, inwestycja zwiększa dostępność dla mieszkańców sąsiednich terenów, sprzyjając rozwojowi miejskiej gospodarki i wzmacniając relacje funkcjonalne w MOF/ZNOF.",
    "styleUrl": "#icon-1886-7CB342",
    "Nr referencyjny umowy": "ZT25-00596",
    "Data zawarcia umowy pożyczki": "2/10/2025",
    "Kwota pożyczki": "  1,650,000.0 ",
    "Nazwa pożyczkobiorcy": "GMINA ŚWIDNICA",
    "Lokalizacja": "51.886571541478475, 15.382544818873686",
    "1 Lokalizacja/Miasto Inwestycji": "Zielona Góra",
    "Opis projektu": "Przedmiotem projektu jest budowa ścieżki rowerowej o łącznej długości ok. 2,5 km relacji Zielona Góra-Wilkanowo – etap II. Projekt realizowany będzie w województwie lubuskim, w gminie wiejskiej Świdnica na terenie MOF/ZNOF.  Wyznaczona trasa przebiegu ścieżki rowerowej na terenie gminy Świdnica przebiega wzdłuż pasa drogi wojewódzkiej nr 282, głównie na terenach leśnych i wzdłuż działek drogowych do ronda południowej obwodnicy miasta Zielona Góra. Jest to kontynuacja budowy ścieżki rowerowej wytyczonej w ramach projektu ODRA-VELO, która  połączy miejscowość Wilkanowo ze ścieżką na terenie miasta Zielona Góra, a docelowo połączy gminy ZNOF od granicy miasta Zielona Góra przez Gminy ZNOF Świdnica - Nowogród Bobrzański. Realizacja projektu przyczyni się do rozwiązania problemów zdiagnozowanych w obszarze transportu  i komunikacji indywidualnej na terenie obszaru ZNOF oraz województwa lubuskiego, czyli zwiększy spójność ścieżek rowerowych, umożliwi dostęp do komunikacji zeroemisyjnej jaką jest transport rowerowy, co będzie miało przełożenie na zmniejszenie zanieczyszczenia powietrza (minimalizacja CO2 do powietrza dzięki zmniejszeniu ruchu tradycyjnego spalinowego na rzecz transportu rowerowego). Zmniejszy zagrożenie wypadkiem z powodu niewystarczającego poziomu infrastruktury dedykowanej rowerzystom, a także wpłynie na poprawę jakości życia i zdrowia mieszkańców. \nZ rezultatów projektu tj. wybudowanego odcinka ścieżki rowerowej będą korzystać osoby bezpośrednio związane z tym terenem tj. mieszkańcy Wilkanowa, Zielonej Góry, Świdnicy jak i Nowogrodu Bobrzańskiego, niemniej jednak cała społeczność regionu odniesie pozytywną korzyść z powstałej infrastruktury poprzez możliwość przebywania w czystszym środowisku, uprawiania turystyki aktywnej oraz zdobycie szerokiej wiedzy na temat otaczającego środowiska naturalnego.\nŚcieżka, łącząc różne obszary w ramach MOF/ZNOF, przyczynia się do poprawy dostępności komunikacyjnej i integracji przestrzennej. Dla obszarów wiejskich oznacza to lepsze możliwości rozwoju turystyki, aktywizacji gospodarczej i poprawę jakości życia. Z kolei dla miasta, takiego jak Zielona Góra, inwestycja zwiększa dostępność dla mieszkańców sąsiednich terenów, sprzyjając rozwojowi miejskiej gospodarki i wzmacniając relacje funkcjonalne w MOF/ZNOF."
}