{
    "name": "Rewaloryzacja Parku Bednarskiego i Wzgórza Lasoty",
    "description": "Nr referencyjny umowy: ZT24-05494<br>Data zawarcia umowy pożyczki: 12/2/2024<br>Kwota pożyczki:   17,440,080.7 <br>Nazwa pożyczkobiorcy: GMINA MIEJSKA KRAKÓW MIASTO NA PRAWACH POWIATU<br>Lokalizacja: 50.04159433712659, 19.948475165704544<br>1 Lokalizacja/Miasto Inwestycji: Kraków<br>Opis projektu: Projekt obejmował kompleksową rewitalizację zabytkowego Parku im. Wojciecha Bednarskiego w Krakowie. Główną przyczyną realizacji zadania był zły stan infrastruktury parku – alejek, małej architektury, jak i zieleni, która wymagała odnowienia, a także konieczność uzupełnienia infrastruktury parku, zgodnie z potrzebami jego użytkowników czyli mieszkańców Krakowa.<br>W ramach projektu dokonano nasadzeń zieleni w tym trawników, drzew, krzewów, bylin oraz roślin cebulowych. Wykonano niezbędne rozbiórki, w tym schodów terenowych, starych nawierzchni, w których miejsce powstały nowe ścieżki i chodniki zapewniające właściwy układ komunikacyjny z uwzględnieniem potrzeb osób z niepełnosprawnych. Zagospodarowanie terenu w ramach projektu dotyczyło także demontażu starych urządzeń i elementów małej architektury oraz montaż nowych urządzeń zabawowych (plac zabaw), wykonanie i montaż urządzeń nowej siłowni plenerowej, doposażenie parku w elementy małej architektury takie jak ławki, stoły, leżaki, kosze na śmieci, tablice informacyjne, tabliczki przyrodnicze, co w znaczący sposób podniosło atrakcyjność parku i możliwość aktywnego spędzenia czasu na jego terenie. W ramach prac budowlano instalacyjnych uzupełniono infrastrukturę sanitarną poprzez budowę budynku toalety tzw. „Domek ogrodnika”, wykonano renowację pomnika patrona parku - Wojciecha Bednarskiego, wykonano także nową nawierzchnię parkingu (wymiana 1:1, stąd brak zmniejszenia powierzchni biologicznie czynnej w tym obszarze, dodatkowo zadbano o miejsca dla osób niepełnosprawnych). W ramach projektu został wyremontowany także budynek Gloriety - (pierwotnie obiekt pełnił funkcję betonowej okrągłej altany). W chwili podjęcia działań obiekt był w bardzo złym stanie technicznym. Aktualnie pełni funkcję kawiarni. Przed realizacją projektu na terenie parku istniały stare sodowe latarnie. W ramach rewitalizacji tam gdzie to było konieczne wymieniono stare latarnie i w ich miejsce zostały zamontowane nowe żeliwne słupy (nawiązujące do historycznych form dawnych latarni) z nowoczesnymi energooszczędnymi oprawami LED. W miejscach dotychczas nie oświetlonych dokonano montażu nowego oświetlenia np. plac zabaw, siłownia, co umożliwiło korzystanie z infrastruktury parku także w godzinach wieczornych. Rezultatem projektu jest nowoczesna - (przy jednoczesnym zachowaniu zabytkowego charakteru parku) - zrewitalizowana przestrzeń publiczna o powierzchni 8,46 ha .",
    "styleUrl": "#icon-1886-7CB342",
    "Nr referencyjny umowy": "ZT24-05494",
    "Data zawarcia umowy pożyczki": "12/2/2024",
    "Kwota pożyczki": "  17,440,080.7 ",
    "Nazwa pożyczkobiorcy": "GMINA MIEJSKA KRAKÓW MIASTO NA PRAWACH POWIATU",
    "Lokalizacja": "50.04159433712659, 19.948475165704544",
    "1 Lokalizacja/Miasto Inwestycji": "Kraków",
    "Opis projektu": "Projekt obejmował kompleksową rewitalizację zabytkowego Parku im. Wojciecha Bednarskiego w Krakowie. Główną przyczyną realizacji zadania był zły stan infrastruktury parku – alejek, małej architektury, jak i zieleni, która wymagała odnowienia, a także konieczność uzupełnienia infrastruktury parku, zgodnie z potrzebami jego użytkowników czyli mieszkańców Krakowa.\nW ramach projektu dokonano nasadzeń zieleni w tym trawników, drzew, krzewów, bylin oraz roślin cebulowych. Wykonano niezbędne rozbiórki, w tym schodów terenowych, starych nawierzchni, w których miejsce powstały nowe ścieżki i chodniki zapewniające właściwy układ komunikacyjny z uwzględnieniem potrzeb osób z niepełnosprawnych. Zagospodarowanie terenu w ramach projektu dotyczyło także demontażu starych urządzeń i elementów małej architektury oraz montaż nowych urządzeń zabawowych (plac zabaw), wykonanie i montaż urządzeń nowej siłowni plenerowej, doposażenie parku w elementy małej architektury takie jak ławki, stoły, leżaki, kosze na śmieci, tablice informacyjne, tabliczki przyrodnicze, co w znaczący sposób podniosło atrakcyjność parku i możliwość aktywnego spędzenia czasu na jego terenie. W ramach prac budowlano instalacyjnych uzupełniono infrastrukturę sanitarną poprzez budowę budynku toalety tzw. „Domek ogrodnika”, wykonano renowację pomnika patrona parku - Wojciecha Bednarskiego, wykonano także nową nawierzchnię parkingu (wymiana 1:1, stąd brak zmniejszenia powierzchni biologicznie czynnej w tym obszarze, dodatkowo zadbano o miejsca dla osób niepełnosprawnych). W ramach projektu został wyremontowany także budynek Gloriety - (pierwotnie obiekt pełnił funkcję betonowej okrągłej altany). W chwili podjęcia działań obiekt był w bardzo złym stanie technicznym. Aktualnie pełni funkcję kawiarni. Przed realizacją projektu na terenie parku istniały stare sodowe latarnie. W ramach rewitalizacji tam gdzie to było konieczne wymieniono stare latarnie i w ich miejsce zostały zamontowane nowe żeliwne słupy (nawiązujące do historycznych form dawnych latarni) z nowoczesnymi energooszczędnymi oprawami LED. W miejscach dotychczas nie oświetlonych dokonano montażu nowego oświetlenia np. plac zabaw, siłownia, co umożliwiło korzystanie z infrastruktury parku także w godzinach wieczornych. Rezultatem projektu jest nowoczesna - (przy jednoczesnym zachowaniu zabytkowego charakteru parku) - zrewitalizowana przestrzeń publiczna o powierzchni 8,46 ha ."
}