[
  {
    "name": "Kasztanowy Ogród Krakowian przy ul. Wita Stwosza",
    "description": "Nr referencyjny umowy: ZT24-05474<br>Data zawarcia umowy pożyczki: 12/2/2024<br>Kwota pożyczki:   1,900,865.2 <br>Nazwa pożyczkobiorcy: GMINA MIEJSKA KRAKÓW MIASTO NA PRAWACH POWIATU<br>Lokalizacja: 50.07198301213973, 19.948450862099826<br>1 Lokalizacja/Miasto Inwestycji: Kraków<br>Opis projektu: Projekt polegał na utworzeniu na terenie Krakowa parku kieszonkowego pn. „Kasztanowy Ogród Krakowian przy ul. Wita Stwosza”. Teren ten był w przeszłości wykorzystywany jako „dziki” parking, a znaczną część terenu stanowiła nawierzchnia utwardzona. Projekt zakładał wykonanie nowej nawierzchni utwardzonej, która została wykonana na mniejszej powierzchni niż stan zastany, co a tym idzie zwiększyła się powierzchnia biologicznie czynna. Projekt zagospodarowania zakładał wykorzystanie istniejącej zieleni. Odtworzono istniejącą aleję, dokonano licznych nasadzeń drzew, krzewów i bylin, zbudowano ścieżki spacerowe, wprowadzono elementy małej architektury (np. huśtawkoławki, ławki, stoliki, kosze na śmieci, stojaki rowerowe) oraz urządzenia zabawowe z drewna przypominające wielkie kasztany. Strefa zabawowa została obsadzona kasztanowcami czerwonymi (10 szt.) oraz oddzielona od ulicy Wita Stwosza murem (ma on za zadanie wygłuszyć hałas ruchu samochodowego), na którym zaprojektowano urządzenia zabawowe/muzyczne oraz zaplanowano obsadzenia pnączami. Na terenie inwestycji nasadzono również 24 szt. lipy drobnolistnej oraz prawie 3,5 tys. krzewów i 5 tys. bylin. Powstanie parku kieszonkowego pozwoliło na stworzenie zielonej przyjaznej przestrzeni publicznej, która stała się miejscem spotkań lokalnej społeczności. Rezultatem projektu jest powstanie zagospodarowanej zielonej przestrzeni publicznej o powierzchni ok. 3000 m2. Projekt wpisuje się również w inne cele ZTM, jak np. zazielenianie terenów miejskich (z uwagi na nowe nasadzenia), poprawę jakości życia i zdrowia mieszkańców (z uwagi na polepszenie możliwości przebywania mieszkańcom na terenie zielonym), łagodzenie zmian klimatu i adaptację do nich (z powodów j/w).",
    "styleUrl": "#icon-1886-7CB342",
    "Nr referencyjny umowy": "ZT24-05474",
    "Data zawarcia umowy pożyczki": "12/2/2024",
    "Kwota pożyczki": "  1,900,865.2 ",
    "Nazwa pożyczkobiorcy": "GMINA MIEJSKA KRAKÓW MIASTO NA PRAWACH POWIATU",
    "Lokalizacja": "50.07198301213973, 19.948450862099826",
    "1 Lokalizacja/Miasto Inwestycji": "Kraków",
    "Opis projektu": "Projekt polegał na utworzeniu na terenie Krakowa parku kieszonkowego pn. „Kasztanowy Ogród Krakowian przy ul. Wita Stwosza”. Teren ten był w przeszłości wykorzystywany jako „dziki” parking, a znaczną część terenu stanowiła nawierzchnia utwardzona. Projekt zakładał wykonanie nowej nawierzchni utwardzonej, która została wykonana na mniejszej powierzchni niż stan zastany, co a tym idzie zwiększyła się powierzchnia biologicznie czynna. Projekt zagospodarowania zakładał wykorzystanie istniejącej zieleni. Odtworzono istniejącą aleję, dokonano licznych nasadzeń drzew, krzewów i bylin, zbudowano ścieżki spacerowe, wprowadzono elementy małej architektury (np. huśtawkoławki, ławki, stoliki, kosze na śmieci, stojaki rowerowe) oraz urządzenia zabawowe z drewna przypominające wielkie kasztany. Strefa zabawowa została obsadzona kasztanowcami czerwonymi (10 szt.) oraz oddzielona od ulicy Wita Stwosza murem (ma on za zadanie wygłuszyć hałas ruchu samochodowego), na którym zaprojektowano urządzenia zabawowe/muzyczne oraz zaplanowano obsadzenia pnączami. Na terenie inwestycji nasadzono również 24 szt. lipy drobnolistnej oraz prawie 3,5 tys. krzewów i 5 tys. bylin. Powstanie parku kieszonkowego pozwoliło na stworzenie zielonej przyjaznej przestrzeni publicznej, która stała się miejscem spotkań lokalnej społeczności. Rezultatem projektu jest powstanie zagospodarowanej zielonej przestrzeni publicznej o powierzchni ok. 3000 m2. Projekt wpisuje się również w inne cele ZTM, jak np. zazielenianie terenów miejskich (z uwagi na nowe nasadzenia), poprawę jakości życia i zdrowia mieszkańców (z uwagi na polepszenie możliwości przebywania mieszkańcom na terenie zielonym), łagodzenie zmian klimatu i adaptację do nich (z powodów j/w)."
  }
]